flyteplayground/__init__.py
flyteplayground/flytectl/__init__.py
flyteplayground/flytectl/task.py
yt_flyte_playground_flytectl-0.1.7.dist-info/METADATA
yt_flyte_playground_flytectl-0.1.7.dist-info/WHEEL
yt_flyte_playground_flytectl-0.1.7.dist-info/top_level.txt
yt_flyte_playground_flytectl-0.1.7.dist-info/RECORD
