Metadata-Version: 2.1
Name: yt-flyte-playground-flytectl
Version: 0.1.7
Summary: This is a demo only.
Home-page: UNKNOWN
Author: wily-coyote
Author-email: queen@borg.hive
License: apache2
Platform: UNKNOWN
Classifier: Programming Language :: Python :: 3.7
Classifier: Programming Language :: Python :: 3.8
Requires-Python: >=3.7
Requires-Dist: flytekit (<1.0.0,>=0.18.0)
